pymupdf_fonts/FiraGO_Bold.py
pymupdf_fonts/FiraGO_BoldItalic.py
pymupdf_fonts/FiraGO_Italic.py
pymupdf_fonts/FiraGO_Regular.py
pymupdf_fonts/FiraMono_Bold.py
pymupdf_fonts/FiraMono_Regular.py
pymupdf_fonts/NotoMusic_Regular.py
pymupdf_fonts/NotoSansMath_Regular.py
pymupdf_fonts/NotoSansSymbols2_Regular.py
pymupdf_fonts/NotoSansSymbols_Regular.py
pymupdf_fonts/NotoSans_Bold.py
pymupdf_fonts/NotoSans_BoldItalic.py
pymupdf_fonts/NotoSans_Italic.py
pymupdf_fonts/NotoSans_Regular.py
pymupdf_fonts/SpaceMono_Bold.py
pymupdf_fonts/SpaceMono_BoldItalic.py
pymupdf_fonts/SpaceMono_Italic.py
pymupdf_fonts/SpaceMono_Regular.py
pymupdf_fonts/__init__.py
pymupdf_fonts-1.0.3.dist-info/LICENSE.txt
pymupdf_fonts-1.0.3.dist-info/METADATA
pymupdf_fonts-1.0.3.dist-info/WHEEL
pymupdf_fonts-1.0.3.dist-info/top_level.txt
pymupdf_fonts-1.0.3.dist-info/RECORD
