Metadata-Version: 2.1
Name: pymupdf-fonts
Version: 1.0.3
Summary: Collection of font binaries for use in PyMuPDF
Home-page: https://github.com/pymupdf/pymupdf_fonts
Author: Jorj McKie
Author-email: jorj.x.mckie@outlook.de
License: UNKNOWN
Platform: UNKNOWN
Classifier: Development Status :: 5 - Production/Stable
Classifier: Environment :: Console
Classifier: Intended Audience :: Developers
Classifier: Programming Language :: Python :: 3
Classifier: Topic :: Utilities
